CHANGELOG.rst
MANIFEST.in
README.rst
setup.py
dougrain/__init__.py
dougrain/builder.py
dougrain/curie.py
dougrain/document.py
dougrain/drafts.py
dougrain/link.py
dougrain.egg-info/PKG-INFO
dougrain.egg-info/SOURCES.txt
dougrain.egg-info/dependency_links.txt
dougrain.egg-info/requires.txt
dougrain.egg-info/top_level.txt
test/test_builder.py
test/test_curie.py
test/test_document.py
test/test_link.py